MANIFEST.in
README
setup.py
django_simple_avatar.egg-info/PKG-INFO
django_simple_avatar.egg-info/SOURCES.txt
django_simple_avatar.egg-info/dependency_links.txt
django_simple_avatar.egg-info/not-zip-safe
django_simple_avatar.egg-info/requires.txt
django_simple_avatar.egg-info/top_level.txt
simpleavatar/__init__.py
simpleavatar/admin.py
simpleavatar/forms.py
simpleavatar/models.py
simpleavatar/settings.py
simpleavatar/urls.py
simpleavatar/views.py
simpleavatar/management/__init__.py
simpleavatar/management/commands/__init__.py
simpleavatar/management/commands/rebuild_avatars.py
simpleavatar/media/avatar/default.jpg
simpleavatar/templates/avatar/base.html
simpleavatar/templates/avatar/change.html
simpleavatar/templatetags/__init__.py
simpleavatar/templatetags/avatar_tags.py