Metadata-Version: 1.0
Name: django-simple-avatar
Version: 0.8.6
Summary: django-simple-avatar
Home-page: https://github.com/vicalloy/django-simple-avatar/
Author: vicalloy
Author-email: zbirder@gmail.com
License: BSD
Keywords: avatar,django
Platform: UNKNOWN
Classifier: Programming Language :: Python
Classifier: Topic :: Software Development :: Libraries :: Python Modules
Classifier: Framework :: Django
Classifier: Environment :: Web Environment
